[
  {
    "tag": [
      {
        "id": "e8e87d1a-6cde-49b1-9112-66f425f00c3c",
        "name": "technology",
        "created_at": "2023-09-21T12:52:08.838Z",
        "updated_at": "2023-09-21T05:29:17.110Z"
      },
      {
        "id": "c65141e5-366b-40b3-8a9b-b90d2d2b15b4",
        "name": "food",
        "created_at": "2023-09-21T06:00:57.869Z",
        "updated_at": "2023-09-20T22:37:04.962Z"
      },
      {
        "id": "92c7c5d9-ef20-4602-b9da-9ea2da7a82bb",
        "name": "travel",
        "created_at": "2023-09-21T13:51:41.072Z",
        "updated_at": "2023-09-21T08:01:32.259Z"
      },
      {
        "id": "22637088-8990-4d34-8b54-05598bd4bf11",
        "name": "music",
        "created_at": "2023-09-21T12:22:17.376Z",
        "updated_at": "2023-09-21T06:09:03.619Z"
      },
      {
        "id": "67ecf143-7569-4900-8d86-96f7ab247ff2",
        "name": "sports",
        "created_at": "2023-09-21T09:46:27.252Z",
        "updated_at": "2023-09-21T11:59:39.969Z"
      }
    ],
    "post": [
      {
        "id": "21b230df-6f8c-4d05-b037-a7280924c05f",
        "title": "The Importance of Learning",
        "content": "Lorem ipsum dolor sit amet, consectetur adipiscing elit.",
        "likes": 78603,
        "dislikes": 68515,
        "created_at": "2023-09-21T00:31:49.450Z",
        "updated_at": "2023-09-20T21:51:32.708Z",
        "user_id": "user_entity_pk"
      },
      {
        "id": "6ebe742d-043e-41d7-bb41-54f6c65456c7",
        "title": "Exploring New Destinations",
        "content": "Nullam ac tortor vel dui interdum efficitur.",
        "likes": 88021,
        "dislikes": 10589,
        "created_at": "2023-09-21T10:45:38.308Z",
        "updated_at": "2023-09-20T21:41:00.136Z",
        "user_id": "user_entity_pk"
      },
      {
        "id": "363e8da9-5798-4bc8-9a6a-b80e23a6dc10",
        "title": "The Art of Cooking",
        "content": "Sed eu nisi auctor, dapibus tellus vitae, fermentum turpis.",
        "likes": 99574,
        "dislikes": 41423,
        "created_at": "2023-09-21T08:57:24.373Z",
        "updated_at": "2023-09-21T04:06:33.922Z",
        "user_id": "user_entity_pk"
      },
      {
        "id": "5cd93651-7468-43eb-ab48-291763cb60df",
        "title": "The Power of Music",
        "content": "Vestibulum vel lectus ac risus finibus auctor.",
        "likes": 44163,
        "dislikes": 35624,
        "created_at": "2023-09-21T14:20:20.287Z",
        "updated_at": "2023-09-20T21:19:29.613Z",
        "user_id": "user_entity_pk"
      },
      {
        "id": "ca41280a-8648-49bf-9cd6-a39a3234a154",
        "title": "Achieving Fitness Goals",
        "content": "Phasellus tincidunt lacus sed semper consectetur.",
        "likes": 7566,
        "dislikes": 93614,
        "created_at": "2023-09-21T01:16:57.671Z",
        "updated_at": "2023-09-21T02:15:04.679Z",
        "user_id": "user_entity_pk"
      }
    ],
    "post_tag": [
      {
        "id": "d5dbcfeb-0377-4806-b14f-6fed6329e33f",
        "created_at": "2023-09-21T05:17:10.878Z",
        "updated_at": "2023-09-20T18:58:04.092Z",
        "post_id": "ca41280a-8648-49bf-9cd6-a39a3234a154",
        "tag_id": "67ecf143-7569-4900-8d86-96f7ab247ff2"
      },
      {
        "id": "e05b6010-bcdf-4fbc-95cd-adf4c7fa1cf1",
        "created_at": "2023-09-20T23:21:01.660Z",
        "updated_at": "2023-09-20T19:34:53.221Z",
        "post_id": "ca41280a-8648-49bf-9cd6-a39a3234a154",
        "tag_id": "c65141e5-366b-40b3-8a9b-b90d2d2b15b4"
      },
      {
        "id": "82f3a999-6330-4343-9d4b-e00e40bf7f91",
        "created_at": "2023-09-21T01:35:50.940Z",
        "updated_at": "2023-09-21T02:08:54.639Z",
        "post_id": "21b230df-6f8c-4d05-b037-a7280924c05f",
        "tag_id": "c65141e5-366b-40b3-8a9b-b90d2d2b15b4"
      },
      {
        "id": "e067fb51-daa9-4fa5-bee5-861462568c91",
        "created_at": "2023-09-20T18:35:11.410Z",
        "updated_at": "2023-09-21T02:14:27.955Z",
        "post_id": "363e8da9-5798-4bc8-9a6a-b80e23a6dc10",
        "tag_id": "67ecf143-7569-4900-8d86-96f7ab247ff2"
      },
      {
        "id": "7ab2d60f-167e-46dc-b07a-848ef5b25828",
        "created_at": "2023-09-20T19:34:55.178Z",
        "updated_at": "2023-09-21T12:20:28.042Z",
        "post_id": "21b230df-6f8c-4d05-b037-a7280924c05f",
        "tag_id": "67ecf143-7569-4900-8d86-96f7ab247ff2"
      }
    ],
    "comment": [
      {
        "id": "562f2212-0b41-47e4-ab5e-d92da6016c19",
        "content": "Great article!",
        "likes": 7723,
        "dislikes": 43753,
        "created_at": "2023-09-21T12:56:09.019Z",
        "updated_at": "2023-09-21T02:57:16.122Z",
        "post_id": "5cd93651-7468-43eb-ab48-291763cb60df",
        "user_id": "user_entity_pk"
      },
      {
        "id": "eb31a212-b1c3-4622-ad5d-041e85fb9bdd",
        "content": "I completely agree.",
        "likes": 94422,
        "dislikes": 19580,
        "created_at": "2023-09-20T19:18:26.666Z",
        "updated_at": "2023-09-21T17:05:19.158Z",
        "post_id": "6ebe742d-043e-41d7-bb41-54f6c65456c7",
        "user_id": "user_entity_pk"
      },
      {
        "id": "a293f8b8-8eac-418a-a981-d16ee74bccfe",
        "content": "Interesting perspective.",
        "likes": 90010,
        "dislikes": 84266,
        "created_at": "2023-09-21T05:53:35.000Z",
        "updated_at": "2023-09-20T18:55:55.424Z",
        "post_id": "21b230df-6f8c-4d05-b037-a7280924c05f",
        "user_id": "user_entity_pk"
      },
      {
        "id": "a1a740b2-2dce-4460-9e62-2c71cfa2e8dc",
        "content": "Thanks for sharing.",
        "likes": 96177,
        "dislikes": 13484,
        "created_at": "2023-09-21T06:33:33.835Z",
        "updated_at": "2023-09-21T09:13:46.218Z",
        "post_id": "ca41280a-8648-49bf-9cd6-a39a3234a154",
        "user_id": "user_entity_pk"
      },
      {
        "id": "5296b3ee-ecb3-48a6-9f32-30f3179a9877",
        "content": "Well written.",
        "likes": 89173,
        "dislikes": 61704,
        "created_at": "2023-09-20T19:24:06.611Z",
        "updated_at": "2023-09-20T23:29:09.790Z",
        "post_id": "5cd93651-7468-43eb-ab48-291763cb60df",
        "user_id": "user_entity_pk"
      }
    ],
    "roqUser": [
      {
        "reference": "58f371bb-8bbf-4482-82c8-3bc1dfab0470",
        "email": "Olga52@roq.tech",
        "firstName": "Helmer",
        "lastName": "Blanda",
        "active": true,
        "avatarUrl": "https://cloudflare-ipfs.com/ipfs/Qmd3W5DuhgHirLHGVixi6V76LhCkZUz6pnFt5AJBiyvHye/avatar/521.jpg",
        "tenantId": null
      },
      {
        "reference": "075e16bc-e2fc-4f0f-bbe4-582fd6d54112",
        "email": "Destiny_Emmerich@roq.tech",
        "firstName": "Myah",
        "lastName": "Wuckert",
        "active": true,
        "avatarUrl": "https://avatars.githubusercontent.com/u/25877291",
        "tenantId": null
      },
      {
        "reference": "782a46c6-9163-4b0b-b423-8411cccc6938",
        "email": "Myles_Metz80@roq.tech",
        "firstName": "Paolo",
        "lastName": "Blanda",
        "active": true,
        "avatarUrl": "https://avatars.githubusercontent.com/u/35250753",
        "tenantId": null
      },
      {
        "reference": "71e92b41-a576-43bd-a77b-28181caf7c61",
        "email": "Norbert_Howell20@roq.tech",
        "firstName": "Jaden",
        "lastName": "Predovic",
        "active": true,
        "avatarUrl": "https://cloudflare-ipfs.com/ipfs/Qmd3W5DuhgHirLHGVixi6V76LhCkZUz6pnFt5AJBiyvHye/avatar/601.jpg",
        "tenantId": null
      },
      {
        "reference": "21aeb10b-ba56-4095-8a73-dc6f0446a9fa",
        "email": "Jeramie17@roq.tech",
        "firstName": "Candelario",
        "lastName": "Lakin",
        "active": true,
        "avatarUrl": "https://avatars.githubusercontent.com/u/47005705",
        "tenantId": null
      }
    ]
  },
  {
    "tag": [
      {
        "id": "a35e5d45-84d7-4b46-bb11-f0d52c83f328",
        "name": "technology",
        "created_at": "2023-09-20T20:10:18.784Z",
        "updated_at": "2023-09-20T23:09:50.778Z"
      },
      {
        "id": "5c42221c-2c2d-434c-bbc0-c28d84dd3a6d",
        "name": "food",
        "created_at": "2023-09-21T11:11:24.170Z",
        "updated_at": "2023-09-21T02:28:28.376Z"
      },
      {
        "id": "4c9c4c12-9659-4a60-9c11-437a8995ad92",
        "name": "travel",
        "created_at": "2023-09-20T19:33:17.982Z",
        "updated_at": "2023-09-21T00:44:05.940Z"
      },
      {
        "id": "79b51116-6b20-4204-9f36-ded390a5d3ed",
        "name": "music",
        "created_at": "2023-09-21T14:49:36.654Z",
        "updated_at": "2023-09-21T17:00:33.937Z"
      },
      {
        "id": "0111f855-25f4-4b23-b831-c11294a736a7",
        "name": "fashion",
        "created_at": "2023-09-21T15:15:09.533Z",
        "updated_at": "2023-09-21T10:28:59.820Z"
      }
    ],
    "post": [
      {
        "id": "fd5ac164-b8d3-4209-bfed-ced13c8d746b",
        "title": "The Art of Programming",
        "content": "Lorem ipsum dolor sit amet, consectetur adipiscing elit.",
        "likes": 58986,
        "dislikes": 74750,
        "created_at": "2023-09-21T07:53:10.246Z",
        "updated_at": "2023-09-21T08:51:06.196Z",
        "user_id": "user_entity_pk"
      },
      {
        "id": "831e0de3-1501-4284-b810-fe65961a27f1",
        "title": "Exploring New Culinary Delights",
        "content": "Sed ut perspiciatis unde omnis iste natus error sit voluptatem accusantium doloremque laudantium.",
        "likes": 44879,
        "dislikes": 17120,
        "created_at": "2023-09-21T13:56:06.614Z",
        "updated_at": "2023-09-20T18:12:42.835Z",
        "user_id": "user_entity_pk"
      },
      {
        "id": "111a30a6-5a87-405f-8757-ee58200b1fbc",
        "title": "Unforgettable Adventures Around the World",
        "content": "Nemo enim ipsam voluptatem quia voluptas sit aspernatur aut odit aut fugit.",
        "likes": 44153,
        "dislikes": 65047,
        "created_at": "2023-09-21T12:39:50.462Z",
        "updated_at": "2023-09-20T22:38:11.319Z",
        "user_id": "user_entity_pk"
      },
      {
        "id": "de9dd242-ba5d-4a9a-9d29-0c476b9a970d",
        "title": "The Power of Music",
        "content": "Neque porro quisquam est, qui dolorem ipsum quia dolor sit amet, consectetur, adipisci velit.",
        "likes": 95752,
        "dislikes": 97368,
        "created_at": "2023-09-21T02:49:52.279Z",
        "updated_at": "2023-09-21T13:13:01.772Z",
        "user_id": "user_entity_pk"
      },
      {
        "id": "570f84d2-54d2-4083-a03b-2fc95709fcbb",
        "title": "Fashion Trends for the Modern Era",
        "content": "Ut enim ad minima veniam, quis nostrum exercitationem ullam corporis suscipit laboriosam.",
        "likes": 87617,
        "dislikes": 10987,
        "created_at": "2023-09-20T20:46:19.387Z",
        "updated_at": "2023-09-21T00:21:42.575Z",
        "user_id": "user_entity_pk"
      }
    ],
    "post_tag": [
      {
        "id": "5dc66673-3c81-4fac-bbe5-00718120a4c1",
        "created_at": "2023-09-20T23:16:03.616Z",
        "updated_at": "2023-09-21T09:43:19.806Z",
        "post_id": "111a30a6-5a87-405f-8757-ee58200b1fbc",
        "tag_id": "79b51116-6b20-4204-9f36-ded390a5d3ed"
      },
      {
        "id": "4aa05b90-89cf-4fe3-a84d-efb58c7ae380",
        "created_at": "2023-09-21T01:30:50.839Z",
        "updated_at": "2023-09-21T05:10:05.676Z",
        "post_id": "111a30a6-5a87-405f-8757-ee58200b1fbc",
        "tag_id": "0111f855-25f4-4b23-b831-c11294a736a7"
      },
      {
        "id": "7bcbccc1-663e-47e8-9da5-17fb8bdf4b5f",
        "created_at": "2023-09-21T13:02:20.602Z",
        "updated_at": "2023-09-20T18:46:35.560Z",
        "post_id": "111a30a6-5a87-405f-8757-ee58200b1fbc",
        "tag_id": "a35e5d45-84d7-4b46-bb11-f0d52c83f328"
      },
      {
        "id": "1bb5e140-620f-4e84-892f-2daa5a38600b",
        "created_at": "2023-09-21T15:56:30.256Z",
        "updated_at": "2023-09-21T09:21:22.918Z",
        "post_id": "831e0de3-1501-4284-b810-fe65961a27f1",
        "tag_id": "4c9c4c12-9659-4a60-9c11-437a8995ad92"
      },
      {
        "id": "72c14f6f-6056-4bc6-8afa-cb34e0b55430",
        "created_at": "2023-09-21T12:56:25.807Z",
        "updated_at": "2023-09-21T06:19:48.032Z",
        "post_id": "fd5ac164-b8d3-4209-bfed-ced13c8d746b",
        "tag_id": "0111f855-25f4-4b23-b831-c11294a736a7"
      }
    ],
    "comment": [
      {
        "id": "c62a238a-69a5-440f-86c4-3215091afdfd",
        "content": "Great article!",
        "likes": 91274,
        "dislikes": 45128,
        "created_at": "2023-09-21T16:18:54.947Z",
        "updated_at": "2023-09-21T16:52:36.114Z",
        "post_id": "831e0de3-1501-4284-b810-fe65961a27f1",
        "user_id": "user_entity_pk"
      },
      {
        "id": "66c3f1df-f07b-4b26-baa6-4de220077a05",
        "content": "I completely agree with your points.",
        "likes": 72153,
        "dislikes": 49045,
        "created_at": "2023-09-21T11:07:50.250Z",
        "updated_at": "2023-09-21T10:26:51.691Z",
        "post_id": "570f84d2-54d2-4083-a03b-2fc95709fcbb",
        "user_id": "user_entity_pk"
      },
      {
        "id": "c3a29d71-942b-4913-88c1-b90d318bd31f",
        "content": "Thanks for sharing this valuable information.",
        "likes": 1993,
        "dislikes": 34477,
        "created_at": "2023-09-20T18:29:10.010Z",
        "updated_at": "2023-09-21T01:37:03.087Z",
        "post_id": "111a30a6-5a87-405f-8757-ee58200b1fbc",
        "user_id": "user_entity_pk"
      },
      {
        "id": "81539f83-8964-4c82-975d-7ba20fbc7842",
        "content": "I have a different perspective on this topic.",
        "likes": 6445,
        "dislikes": 35326,
        "created_at": "2023-09-21T14:33:02.723Z",
        "updated_at": "2023-09-21T14:34:04.311Z",
        "post_id": "570f84d2-54d2-4083-a03b-2fc95709fcbb",
        "user_id": "user_entity_pk"
      },
      {
        "id": "e74c84f9-4f24-4570-acc6-505c3aa7a9ad",
        "content": "Looking forward to more insightful content.",
        "likes": 28741,
        "dislikes": 80595,
        "created_at": "2023-09-21T06:24:05.710Z",
        "updated_at": "2023-09-21T01:43:24.594Z",
        "post_id": "de9dd242-ba5d-4a9a-9d29-0c476b9a970d",
        "user_id": "user_entity_pk"
      }
    ],
    "roqUser": [
      {
        "reference": "f804edd8-117b-4ae5-9260-bf74b68be524",
        "email": "Kenna_Nikolaus@roq.tech",
        "firstName": "Matilda",
        "lastName": "Walter",
        "active": true,
        "avatarUrl": "https://cloudflare-ipfs.com/ipfs/Qmd3W5DuhgHirLHGVixi6V76LhCkZUz6pnFt5AJBiyvHye/avatar/759.jpg",
        "tenantId": null
      },
      {
        "reference": "76d8817a-939d-4ee1-a451-80a50bc94289",
        "email": "Arvid44@roq.tech",
        "firstName": "Millie",
        "lastName": "Kuhn",
        "active": true,
        "avatarUrl": "https://avatars.githubusercontent.com/u/59697240",
        "tenantId": null
      },
      {
        "reference": "68189111-ed00-4040-bd81-d94a2fb229a0",
        "email": "Dena29@roq.tech",
        "firstName": "Mellie",
        "lastName": "Kub",
        "active": true,
        "avatarUrl": "https://avatars.githubusercontent.com/u/71832110",
        "tenantId": null
      },
      {
        "reference": "65de62c2-6816-4b36-92de-91b9e898db0b",
        "email": "Adrain.Halvorson69@roq.tech",
        "firstName": "Coy",
        "lastName": "Johnston",
        "active": true,
        "avatarUrl": "https://avatars.githubusercontent.com/u/64363160",
        "tenantId": null
      },
      {
        "reference": "1d551d33-0f73-488e-aa96-672eb4b4bb4f",
        "email": "Angel.Conroy@roq.tech",
        "firstName": "Anastacio",
        "lastName": "Lemke",
        "active": true,
        "avatarUrl": "https://cloudflare-ipfs.com/ipfs/Qmd3W5DuhgHirLHGVixi6V76LhCkZUz6pnFt5AJBiyvHye/avatar/634.jpg",
        "tenantId": null
      }
    ]
  },
  {
    "tag": [
      {
        "id": "f447e5d9-d00e-408f-8218-604b2d0e850f",
        "name": "technology",
        "created_at": "2023-09-21T07:19:40.472Z",
        "updated_at": "2023-09-21T17:41:17.864Z"
      },
      {
        "id": "3affa247-d5fc-4021-866f-0ef6fa952ae2",
        "name": "fashion",
        "created_at": "2023-09-21T17:13:18.990Z",
        "updated_at": "2023-09-20T19:27:41.805Z"
      },
      {
        "id": "810e8391-975d-4dbe-bf3f-697a11934478",
        "name": "food",
        "created_at": "2023-09-21T04:19:18.857Z",
        "updated_at": "2023-09-20T23:49:26.535Z"
      },
      {
        "id": "7a26c1fd-ca0c-4402-a3ca-89921577c212",
        "name": "travel",
        "created_at": "2023-09-20T18:19:34.839Z",
        "updated_at": "2023-09-20T21:46:17.365Z"
      },
      {
        "id": "25e4cad0-363c-4a5e-993d-0b930027511e",
        "name": "sports",
        "created_at": "2023-09-20T21:26:25.658Z",
        "updated_at": "2023-09-20T22:46:53.572Z"
      }
    ],
    "post": [
      {
        "id": "3785af38-da9c-4439-908a-b9844258dfbf",
        "title": "Introduction to JavaScript",
        "content": "Learn the basics of JavaScript programming language.",
        "likes": 66076,
        "dislikes": 43405,
        "created_at": "2023-09-21T10:04:36.853Z",
        "updated_at": "2023-09-21T11:23:52.916Z",
        "user_id": "user_entity_pk"
      },
      {
        "id": "e86476b9-53b1-41eb-b92a-3bf18c46d43b",
        "title": "Latest Fashion Trends",
        "content": "Discover the latest fashion trends for this season.",
        "likes": 32792,
        "dislikes": 71562,
        "created_at": "2023-09-21T01:27:38.794Z",
        "updated_at": "2023-09-21T04:17:54.617Z",
        "user_id": "user_entity_pk"
      },
      {
        "id": "f21bd6ba-9090-4482-a20e-cb361b5b6bb1",
        "title": "Delicious Recipes for Summer",
        "content": "Try these delicious recipes to beat the summer heat.",
        "likes": 66006,
        "dislikes": 43914,
        "created_at": "2023-09-21T14:40:32.635Z",
        "updated_at": "2023-09-21T06:03:39.108Z",
        "user_id": "user_entity_pk"
      },
      {
        "id": "23d0ae89-172e-4c60-83d9-6556d1350ee6",
        "title": "Top Travel Destinations",
        "content": "Explore the top travel destinations around the world.",
        "likes": 51019,
        "dislikes": 89211,
        "created_at": "2023-09-21T15:16:30.971Z",
        "updated_at": "2023-09-21T06:22:19.880Z",
        "user_id": "user_entity_pk"
      },
      {
        "id": "8eef3bbf-9dd6-42db-b78e-c395f8787369",
        "title": "Sports Events in 2021",
        "content": "Stay updated with the latest sports events happening in 2021.",
        "likes": 90978,
        "dislikes": 66798,
        "created_at": "2023-09-21T00:03:16.093Z",
        "updated_at": "2023-09-21T05:43:47.234Z",
        "user_id": "user_entity_pk"
      }
    ],
    "post_tag": [
      {
        "id": "4dca1c47-9da3-4c17-826c-7f43449a8fa1",
        "created_at": "2023-09-20T19:02:51.848Z",
        "updated_at": "2023-09-20T19:40:59.086Z",
        "post_id": "3785af38-da9c-4439-908a-b9844258dfbf",
        "tag_id": "3affa247-d5fc-4021-866f-0ef6fa952ae2"
      },
      {
        "id": "0c8dc88b-5d02-4a44-b286-8b944d8fd3e3",
        "created_at": "2023-09-20T22:07:41.210Z",
        "updated_at": "2023-09-21T02:43:46.548Z",
        "post_id": "f21bd6ba-9090-4482-a20e-cb361b5b6bb1",
        "tag_id": "3affa247-d5fc-4021-866f-0ef6fa952ae2"
      },
      {
        "id": "8aee82fc-78a8-4f00-b260-17e6597255b6",
        "created_at": "2023-09-21T15:25:18.787Z",
        "updated_at": "2023-09-20T19:46:50.946Z",
        "post_id": "8eef3bbf-9dd6-42db-b78e-c395f8787369",
        "tag_id": "810e8391-975d-4dbe-bf3f-697a11934478"
      },
      {
        "id": "66808aad-3509-46f7-bf74-5e593a48e7a1",
        "created_at": "2023-09-21T12:22:04.521Z",
        "updated_at": "2023-09-21T14:18:07.895Z",
        "post_id": "3785af38-da9c-4439-908a-b9844258dfbf",
        "tag_id": "25e4cad0-363c-4a5e-993d-0b930027511e"
      },
      {
        "id": "c73b4a89-0b26-424b-a11e-d17b2155122c",
        "created_at": "2023-09-20T21:28:46.884Z",
        "updated_at": "2023-09-21T13:21:29.411Z",
        "post_id": "8eef3bbf-9dd6-42db-b78e-c395f8787369",
        "tag_id": "810e8391-975d-4dbe-bf3f-697a11934478"
      }
    ],
    "comment": [
      {
        "id": "6fa5e5ee-0f63-4844-bafb-edc2e0fa91dc",
        "content": "Great article!",
        "likes": 5944,
        "dislikes": 71262,
        "created_at": "2023-09-20T23:00:51.806Z",
        "updated_at": "2023-09-21T00:04:13.078Z",
        "post_id": "23d0ae89-172e-4c60-83d9-6556d1350ee6",
        "user_id": "user_entity_pk"
      },
      {
        "id": "b606dc48-5e7a-49ca-afd6-a9d451cf1bb4",
        "content": "I love this outfit!",
        "likes": 44588,
        "dislikes": 69363,
        "created_at": "2023-09-21T12:03:43.355Z",
        "updated_at": "2023-09-21T11:03:37.611Z",
        "post_id": "23d0ae89-172e-4c60-83d9-6556d1350ee6",
        "user_id": "user_entity_pk"
      },
      {
        "id": "648536ac-cfec-4ded-9dee-b47eec438287",
        "content": "The recipe turned out amazing!",
        "likes": 27348,
        "dislikes": 43745,
        "created_at": "2023-09-20T20:20:42.491Z",
        "updated_at": "2023-09-21T03:08:22.152Z",
        "post_id": "e86476b9-53b1-41eb-b92a-3bf18c46d43b",
        "user_id": "user_entity_pk"
      },
      {
        "id": "1b54c1ae-1474-445b-8c9b-e622b5954f37",
        "content": "I've always wanted to visit this place.",
        "likes": 18414,
        "dislikes": 69693,
        "created_at": "2023-09-21T09:59:21.610Z",
        "updated_at": "2023-09-20T22:17:14.022Z",
        "post_id": "3785af38-da9c-4439-908a-b9844258dfbf",
        "user_id": "user_entity_pk"
      },
      {
        "id": "2f93d83b-a42c-49d5-9266-ba1871e721ba",
        "content": "Can't wait for the upcoming game!",
        "likes": 63276,
        "dislikes": 10974,
        "created_at": "2023-09-21T02:55:22.921Z",
        "updated_at": "2023-09-21T06:18:49.032Z",
        "post_id": "f21bd6ba-9090-4482-a20e-cb361b5b6bb1",
        "user_id": "user_entity_pk"
      }
    ],
    "roqUser": [
      {
        "reference": "ae0b1d73-ade5-46a8-8b1c-19d820518b23",
        "email": "Paxton88@roq.tech",
        "firstName": "Norris",
        "lastName": "Halvorson",
        "active": true,
        "avatarUrl": "https://cloudflare-ipfs.com/ipfs/Qmd3W5DuhgHirLHGVixi6V76LhCkZUz6pnFt5AJBiyvHye/avatar/1026.jpg",
        "tenantId": null
      },
      {
        "reference": "ccc2e3de-2838-4e9a-8ac5-4e36ec163ab8",
        "email": "Jamar61@roq.tech",
        "firstName": "Aric",
        "lastName": "Koch",
        "active": true,
        "avatarUrl": "https://cloudflare-ipfs.com/ipfs/Qmd3W5DuhgHirLHGVixi6V76LhCkZUz6pnFt5AJBiyvHye/avatar/587.jpg",
        "tenantId": null
      },
      {
        "reference": "b07735b6-fc35-455d-b91e-aa83427403a5",
        "email": "Reilly71@roq.tech",
        "firstName": "Jenifer",
        "lastName": "Farrell",
        "active": true,
        "avatarUrl": "https://cloudflare-ipfs.com/ipfs/Qmd3W5DuhgHirLHGVixi6V76LhCkZUz6pnFt5AJBiyvHye/avatar/465.jpg",
        "tenantId": null
      },
      {
        "reference": "2c43570b-80ee-4bf4-8574-fa0479c10089",
        "email": "Bobbie_Mante@roq.tech",
        "firstName": "Korbin",
        "lastName": "Wiegand",
        "active": true,
        "avatarUrl": "https://avatars.githubusercontent.com/u/82863315",
        "tenantId": null
      },
      {
        "reference": "00b2fdf6-ca6e-49a6-bcd2-c00f1e4728d2",
        "email": "Tillman56@roq.tech",
        "firstName": "Estefania",
        "lastName": "Cremin",
        "active": true,
        "avatarUrl": "https://avatars.githubusercontent.com/u/43858038",
        "tenantId": null
      }
    ]
  },
  {
    "tag": [
      {
        "id": "4891540a-f142-4534-94a8-5c20ed995e5a",
        "name": "technology",
        "created_at": "2023-09-20T19:02:36.882Z",
        "updated_at": "2023-09-21T02:17:34.016Z"
      },
      {
        "id": "09837d48-755f-4d47-8b1e-8c09997aa187",
        "name": "food",
        "created_at": "2023-09-21T15:00:16.276Z",
        "updated_at": "2023-09-21T08:31:57.453Z"
      },
      {
        "id": "520fd4cb-da27-4c43-a858-beab019e82e2",
        "name": "travel",
        "created_at": "2023-09-21T08:38:35.945Z",
        "updated_at": "2023-09-20T19:44:51.927Z"
      },
      {
        "id": "7181c4e6-eef6-4504-8f57-1e7e99185a47",
        "name": "music",
        "created_at": "2023-09-21T04:32:56.008Z",
        "updated_at": "2023-09-20T22:22:33.835Z"
      },
      {
        "id": "04ff7120-74cf-43e1-8c71-592ffbe1248a",
        "name": "sports",
        "created_at": "2023-09-21T03:23:59.033Z",
        "updated_at": "2023-09-21T11:48:30.276Z"
      }
    ],
    "post": [
      {
        "id": "db0d11b2-63dc-4888-a0b8-7fc9ea4fbeb0",
        "title": "The Importance of Coding",
        "content": "Lorem ipsum dolor sit amet, consectetur adipiscing elit.",
        "likes": 64264,
        "dislikes": 21559,
        "created_at": "2023-09-21T03:14:30.894Z",
        "updated_at": "2023-09-20T20:43:48.466Z",
        "user_id": "user_entity_pk"
      },
      {
        "id": "f7a23469-2ef7-4540-9ca8-f88f898dd665",
        "title": "Delicious Recipes to Try",
        "content": "Sed ut perspiciatis unde omnis iste natus error sit voluptatem accusantium doloremque laudantium.",
        "likes": 78871,
        "dislikes": 57359,
        "created_at": "2023-09-21T02:07:58.327Z",
        "updated_at": "2023-09-21T11:04:26.372Z",
        "user_id": "user_entity_pk"
      },
      {
        "id": "2d3ea3c0-442e-47e4-9cc9-1aafc3cf3b6b",
        "title": "Exploring the Wonders of the World",
        "content": "Nemo enim ipsam voluptatem quia voluptas sit aspernatur aut odit aut fugit.",
        "likes": 58809,
        "dislikes": 77569,
        "created_at": "2023-09-21T05:58:03.882Z",
        "updated_at": "2023-09-21T04:52:58.825Z",
        "user_id": "user_entity_pk"
      },
      {
        "id": "22294e36-b204-48a6-8a33-1e4606cdd1dd",
        "title": "The Power of Music",
        "content": "Ut enim ad minima veniam, quis nostrum exercitationem ullam corporis suscipit laboriosam.",
        "likes": 39311,
        "dislikes": 92612,
        "created_at": "2023-09-20T19:39:13.088Z",
        "updated_at": "2023-09-21T06:24:02.619Z",
        "user_id": "user_entity_pk"
      },
      {
        "id": "d2991dc7-e71b-4dbd-a5ea-362334ea2829",
        "title": "Achieving Success in Sports",
        "content": "Quis autem vel eum iure reprehenderit qui in ea voluptate velit esse quam nihil molestiae consequatur.",
        "likes": 91274,
        "dislikes": 49807,
        "created_at": "2023-09-21T07:40:28.619Z",
        "updated_at": "2023-09-21T00:01:13.050Z",
        "user_id": "user_entity_pk"
      }
    ],
    "post_tag": [
      {
        "id": "242f61d0-d7f9-4eaa-a475-508bab66ad62",
        "created_at": "2023-09-21T15:45:06.603Z",
        "updated_at": "2023-09-21T03:40:36.994Z",
        "post_id": "22294e36-b204-48a6-8a33-1e4606cdd1dd",
        "tag_id": "09837d48-755f-4d47-8b1e-8c09997aa187"
      },
      {
        "id": "bedb6683-9a81-4a0a-a81c-79c48d862565",
        "created_at": "2023-09-20T19:57:44.569Z",
        "updated_at": "2023-09-21T17:05:58.443Z",
        "post_id": "db0d11b2-63dc-4888-a0b8-7fc9ea4fbeb0",
        "tag_id": "7181c4e6-eef6-4504-8f57-1e7e99185a47"
      },
      {
        "id": "95c72a18-a15c-4219-abdc-15b16ebbf2c0",
        "created_at": "2023-09-21T06:16:06.319Z",
        "updated_at": "2023-09-21T01:01:40.471Z",
        "post_id": "d2991dc7-e71b-4dbd-a5ea-362334ea2829",
        "tag_id": "04ff7120-74cf-43e1-8c71-592ffbe1248a"
      },
      {
        "id": "3c446044-6caa-45a0-8287-0d5ba08619e5",
        "created_at": "2023-09-20T18:02:33.683Z",
        "updated_at": "2023-09-21T06:37:31.389Z",
        "post_id": "db0d11b2-63dc-4888-a0b8-7fc9ea4fbeb0",
        "tag_id": "7181c4e6-eef6-4504-8f57-1e7e99185a47"
      },
      {
        "id": "f4fb1891-84d4-4841-b52f-61982fe38a67",
        "created_at": "2023-09-21T02:44:33.752Z",
        "updated_at": "2023-09-21T10:41:45.440Z",
        "post_id": "22294e36-b204-48a6-8a33-1e4606cdd1dd",
        "tag_id": "4891540a-f142-4534-94a8-5c20ed995e5a"
      }
    ],
    "comment": [
      {
        "id": "cbc1260b-b9c0-4816-aad3-a788e7816802",
        "content": "Great article!",
        "likes": 63059,
        "dislikes": 97334,
        "created_at": "2023-09-21T01:34:51.992Z",
        "updated_at": "2023-09-21T09:36:59.067Z",
        "post_id": "f7a23469-2ef7-4540-9ca8-f88f898dd665",
        "user_id": "user_entity_pk"
      },
      {
        "id": "0101b1f1-120b-45a6-9a94-f6ba2bca31da",
        "content": "I completely agree.",
        "likes": 3130,
        "dislikes": 89697,
        "created_at": "2023-09-21T14:04:09.325Z",
        "updated_at": "2023-09-21T14:23:31.612Z",
        "post_id": "2d3ea3c0-442e-47e4-9cc9-1aafc3cf3b6b",
        "user_id": "user_entity_pk"
      },
      {
        "id": "ee73fb8b-50cf-4fdf-b096-1929b3b18c53",
        "content": "Thanks for sharing.",
        "likes": 17664,
        "dislikes": 21307,
        "created_at": "2023-09-21T16:46:32.658Z",
        "updated_at": "2023-09-21T16:21:23.499Z",
        "post_id": "2d3ea3c0-442e-47e4-9cc9-1aafc3cf3b6b",
        "user_id": "user_entity_pk"
      },
      {
        "id": "098d5a0c-ecad-4ca7-9b4c-fdb6c2c3e31d",
        "content": "Interesting perspective.",
        "likes": 29722,
        "dislikes": 27871,
        "created_at": "2023-09-21T15:30:11.028Z",
        "updated_at": "2023-09-21T07:49:34.711Z",
        "post_id": "d2991dc7-e71b-4dbd-a5ea-362334ea2829",
        "user_id": "user_entity_pk"
      },
      {
        "id": "05db5f30-af28-40a7-b744-c673df9c2aab",
        "content": "Well written.",
        "likes": 26797,
        "dislikes": 34340,
        "created_at": "2023-09-21T05:18:27.983Z",
        "updated_at": "2023-09-20T18:59:18.585Z",
        "post_id": "db0d11b2-63dc-4888-a0b8-7fc9ea4fbeb0",
        "user_id": "user_entity_pk"
      }
    ],
    "roqUser": [
      {
        "reference": "5680a0a8-a08c-4f16-8f3e-188d8d01d5d0",
        "email": "Cathy_Thompson61@roq.tech",
        "firstName": "Dalton",
        "lastName": "Graham",
        "active": true,
        "avatarUrl": "https://cloudflare-ipfs.com/ipfs/Qmd3W5DuhgHirLHGVixi6V76LhCkZUz6pnFt5AJBiyvHye/avatar/1144.jpg",
        "tenantId": null
      },
      {
        "reference": "44864024-0751-4683-9af2-fa19faba1016",
        "email": "Mattie80@roq.tech",
        "firstName": "Alisa",
        "lastName": "Konopelski",
        "active": true,
        "avatarUrl": "https://cloudflare-ipfs.com/ipfs/Qmd3W5DuhgHirLHGVixi6V76LhCkZUz6pnFt5AJBiyvHye/avatar/1242.jpg",
        "tenantId": null
      },
      {
        "reference": "9c89a7b2-90ef-47c3-850a-40e79dc40201",
        "email": "Duane.Pollich5@roq.tech",
        "firstName": "Kristoffer",
        "lastName": "Bode",
        "active": true,
        "avatarUrl": "https://cloudflare-ipfs.com/ipfs/Qmd3W5DuhgHirLHGVixi6V76LhCkZUz6pnFt5AJBiyvHye/avatar/301.jpg",
        "tenantId": null
      },
      {
        "reference": "d2e71280-18ea-42d6-bbe6-5c783cbeced5",
        "email": "Demario_Ward@roq.tech",
        "firstName": "Ramiro",
        "lastName": "Will",
        "active": true,
        "avatarUrl": "https://cloudflare-ipfs.com/ipfs/Qmd3W5DuhgHirLHGVixi6V76LhCkZUz6pnFt5AJBiyvHye/avatar/1090.jpg",
        "tenantId": null
      },
      {
        "reference": "3c069e20-7683-46e1-80fd-ecc43e40c033",
        "email": "Otto.McCullough@roq.tech",
        "firstName": "Coty",
        "lastName": "Skiles",
        "active": true,
        "avatarUrl": "https://cloudflare-ipfs.com/ipfs/Qmd3W5DuhgHirLHGVixi6V76LhCkZUz6pnFt5AJBiyvHye/avatar/226.jpg",
        "tenantId": null
      }
    ]
  },
  {
    "tag": [
      {
        "id": "6d3b3ac6-4d1a-49de-aba9-a75ddf866755",
        "name": "technology",
        "created_at": "2023-09-21T17:15:27.404Z",
        "updated_at": "2023-09-20T20:39:32.287Z"
      },
      {
        "id": "9e9060f8-8d0e-423f-8af5-9d149ad991da",
        "name": "food",
        "created_at": "2023-09-21T00:34:35.679Z",
        "updated_at": "2023-09-21T17:15:36.865Z"
      },
      {
        "id": "7e56a9f8-52a6-4f87-895c-155c580204e6",
        "name": "travel",
        "created_at": "2023-09-21T07:22:47.066Z",
        "updated_at": "2023-09-21T15:27:20.026Z"
      },
      {
        "id": "bbd02b92-6772-495a-a177-e1113d923aa3",
        "name": "fashion",
        "created_at": "2023-09-20T20:30:36.332Z",
        "updated_at": "2023-09-21T13:43:05.764Z"
      },
      {
        "id": "b3aa92dd-e9f1-4eaa-bf37-e5c506d738c9",
        "name": "sports",
        "created_at": "2023-09-21T17:12:38.071Z",
        "updated_at": "2023-09-21T14:06:09.498Z"
      }
    ],
    "post": [
      {
        "id": "4c5c2fcf-9891-474d-96e1-c28113bf37f5",
        "title": "Introduction to JavaScript",
        "content": "In this article, we will explore the basics of JavaScript programming language.",
        "likes": 41812,
        "dislikes": 66933,
        "created_at": "2023-09-21T06:56:55.098Z",
        "updated_at": "2023-09-20T23:35:46.956Z",
        "user_id": "user_entity_pk"
      },
      {
        "id": "f646731c-8c47-4eb9-840c-50f8d1abe027",
        "title": "Delicious Recipes for Dinner",
        "content": "Try these mouth-watering recipes for a satisfying dinner.",
        "likes": 92245,
        "dislikes": 97443,
        "created_at": "2023-09-21T02:17:00.789Z",
        "updated_at": "2023-09-20T23:32:02.184Z",
        "user_id": "user_entity_pk"
      },
      {
        "id": "232f2863-3a9f-493d-86f1-260f3ca451d9",
        "title": "Top Travel Destinations in Europe",
        "content": "Discover the most beautiful places to visit in Europe.",
        "likes": 91684,
        "dislikes": 75131,
        "created_at": "2023-09-21T11:21:07.343Z",
        "updated_at": "2023-09-21T03:40:09.327Z",
        "user_id": "user_entity_pk"
      },
      {
        "id": "f2243976-ca6b-4bb4-8939-f5e391a3f087",
        "title": "Latest Fashion Trends",
        "content": "Stay updated with the latest fashion trends and styles.",
        "likes": 61044,
        "dislikes": 49543,
        "created_at": "2023-09-20T21:57:24.869Z",
        "updated_at": "2023-09-21T05:44:23.341Z",
        "user_id": "user_entity_pk"
      },
      {
        "id": "995bc631-3a4b-43ad-939e-0527239fc104",
        "title": "Benefits of Regular Exercise",
        "content": "Learn about the numerous benefits of regular exercise for your health.",
        "likes": 12532,
        "dislikes": 40148,
        "created_at": "2023-09-21T14:29:46.615Z",
        "updated_at": "2023-09-21T16:59:59.429Z",
        "user_id": "user_entity_pk"
      }
    ],
    "post_tag": [
      {
        "id": "9f34037b-5738-412f-918a-015958cf1787",
        "created_at": "2023-09-21T06:23:18.445Z",
        "updated_at": "2023-09-21T01:51:41.442Z",
        "post_id": "995bc631-3a4b-43ad-939e-0527239fc104",
        "tag_id": "6d3b3ac6-4d1a-49de-aba9-a75ddf866755"
      },
      {
        "id": "8139808e-f37d-4a29-b3f0-cfba2dd81811",
        "created_at": "2023-09-21T02:38:27.457Z",
        "updated_at": "2023-09-21T07:44:35.083Z",
        "post_id": "232f2863-3a9f-493d-86f1-260f3ca451d9",
        "tag_id": "9e9060f8-8d0e-423f-8af5-9d149ad991da"
      },
      {
        "id": "000ed854-b034-40f4-829c-a3b7776c9587",
        "created_at": "2023-09-21T09:26:24.008Z",
        "updated_at": "2023-09-21T15:16:37.102Z",
        "post_id": "f2243976-ca6b-4bb4-8939-f5e391a3f087",
        "tag_id": "9e9060f8-8d0e-423f-8af5-9d149ad991da"
      },
      {
        "id": "bc123652-6e21-44bb-80b2-969d8a095224",
        "created_at": "2023-09-20T20:30:37.323Z",
        "updated_at": "2023-09-21T07:01:54.862Z",
        "post_id": "4c5c2fcf-9891-474d-96e1-c28113bf37f5",
        "tag_id": "9e9060f8-8d0e-423f-8af5-9d149ad991da"
      },
      {
        "id": "1993aac0-7d43-4c41-8e28-c3bc23075f7a",
        "created_at": "2023-09-20T19:48:49.293Z",
        "updated_at": "2023-09-21T14:37:04.654Z",
        "post_id": "995bc631-3a4b-43ad-939e-0527239fc104",
        "tag_id": "7e56a9f8-52a6-4f87-895c-155c580204e6"
      }
    ],
    "comment": [
      {
        "id": "d85deda5-7efb-4d91-831a-20bfbc153ceb",
        "content": "Great article! Really helpful.",
        "likes": 90049,
        "dislikes": 18453,
        "created_at": "2023-09-20T18:31:53.558Z",
        "updated_at": "2023-09-21T11:21:40.762Z",
        "post_id": "995bc631-3a4b-43ad-939e-0527239fc104",
        "user_id": "user_entity_pk"
      },
      {
        "id": "8f48d140-be8a-4a5b-ac04-9bb61323269d",
        "content": "The recipe turned out amazing. Thanks!",
        "likes": 18081,
        "dislikes": 95265,
        "created_at": "2023-09-21T00:52:27.440Z",
        "updated_at": "2023-09-21T10:25:50.442Z",
        "post_id": "232f2863-3a9f-493d-86f1-260f3ca451d9",
        "user_id": "user_entity_pk"
      },
      {
        "id": "68c1bc4d-9cba-454f-85cc-ee261cb38c03",
        "content": "I've always wanted to visit Europe. Can't wait!",
        "likes": 81862,
        "dislikes": 96723,
        "created_at": "2023-09-21T16:14:46.736Z",
        "updated_at": "2023-09-21T01:49:02.562Z",
        "post_id": "4c5c2fcf-9891-474d-96e1-c28113bf37f5",
        "user_id": "user_entity_pk"
      },
      {
        "id": "5664a84f-304f-47eb-bcd7-892d456b4f9a",
        "content": "Love the latest fashion trends. So stylish!",
        "likes": 9733,
        "dislikes": 90153,
        "created_at": "2023-09-20T21:10:33.190Z",
        "updated_at": "2023-09-21T15:50:49.358Z",
        "post_id": "232f2863-3a9f-493d-86f1-260f3ca451d9",
        "user_id": "user_entity_pk"
      },
      {
        "id": "52ae12e6-85e2-455c-a64c-7d1fa98ffc08",
        "content": "Exercise has made a huge difference in my life.",
        "likes": 68103,
        "dislikes": 45945,
        "created_at": "2023-09-21T07:04:42.896Z",
        "updated_at": "2023-09-21T08:41:42.403Z",
        "post_id": "995bc631-3a4b-43ad-939e-0527239fc104",
        "user_id": "user_entity_pk"
      }
    ],
    "roqUser": [
      {
        "reference": "b37645fd-069d-4dff-9d90-1107c8bc0fe1",
        "email": "Oswald.Wilderman85@roq.tech",
        "firstName": "Eryn",
        "lastName": "Grant",
        "active": true,
        "avatarUrl": "https://avatars.githubusercontent.com/u/91500856",
        "tenantId": null
      },
      {
        "reference": "96667249-3173-44f8-aa6b-1a6b6991ef36",
        "email": "Emilie1@roq.tech",
        "firstName": "Mireya",
        "lastName": "Kuhic",
        "active": true,
        "avatarUrl": "https://cloudflare-ipfs.com/ipfs/Qmd3W5DuhgHirLHGVixi6V76LhCkZUz6pnFt5AJBiyvHye/avatar/594.jpg",
        "tenantId": null
      },
      {
        "reference": "3dad671a-aaf6-4b06-a460-8bcb1e8ee109",
        "email": "Abelardo_Maggio85@roq.tech",
        "firstName": "Friedrich",
        "lastName": "Adams",
        "active": true,
        "avatarUrl": "https://avatars.githubusercontent.com/u/87116118",
        "tenantId": null
      },
      {
        "reference": "3949c66b-e433-4445-a815-9fb17223318f",
        "email": "Katlyn80@roq.tech",
        "firstName": "Julie",
        "lastName": "Lubowitz",
        "active": true,
        "avatarUrl": "https://cloudflare-ipfs.com/ipfs/Qmd3W5DuhgHirLHGVixi6V76LhCkZUz6pnFt5AJBiyvHye/avatar/1207.jpg",
        "tenantId": null
      },
      {
        "reference": "80cc0f8e-b008-4513-9f36-9b89d5be0758",
        "email": "Kamren_Bauch27@roq.tech",
        "firstName": "Demond",
        "lastName": "Denesik",
        "active": true,
        "avatarUrl": "https://cloudflare-ipfs.com/ipfs/Qmd3W5DuhgHirLHGVixi6V76LhCkZUz6pnFt5AJBiyvHye/avatar/824.jpg",
        "tenantId": null
      }
    ]
  },
  {
    "tag": [
      {
        "id": "1c7a13c0-03d5-4f4e-a815-88cd8fc1f5cb",
        "name": "technology",
        "created_at": "2023-09-20T21:46:52.857Z",
        "updated_at": "2023-09-21T01:44:27.800Z"
      },
      {
        "id": "94a8c466-8aaa-4f86-af08-f08262081ab0",
        "name": "food",
        "created_at": "2023-09-21T03:12:05.290Z",
        "updated_at": "2023-09-20T19:57:51.349Z"
      },
      {
        "id": "65683a34-fa24-46b4-8582-1ba2b64c411a",
        "name": "travel",
        "created_at": "2023-09-21T10:22:17.357Z",
        "updated_at": "2023-09-20T20:12:19.981Z"
      },
      {
        "id": "bc06c3c6-b84a-4876-bd9d-605d3ddb0a6a",
        "name": "music",
        "created_at": "2023-09-21T12:14:47.797Z",
        "updated_at": "2023-09-21T11:02:30.447Z"
      },
      {
        "id": "1a1e780b-b83f-497e-b561-65a1f30e0bd8",
        "name": "sports",
        "created_at": "2023-09-21T10:11:24.457Z",
        "updated_at": "2023-09-21T04:53:27.324Z"
      }
    ],
    "post": [
      {
        "id": "44062436-6a25-472c-afb4-f63b2f80a25e",
        "title": "The Art of Coding",
        "content": "In today's digital age...",
        "likes": 10026,
        "dislikes": 42975,
        "created_at": "2023-09-21T03:50:06.086Z",
        "updated_at": "2023-09-20T23:07:35.671Z",
        "user_id": "user_entity_pk"
      },
      {
        "id": "bc888a31-94f0-4d27-86d7-832be21044db",
        "title": "Exploring New Flavors",
        "content": "As a food lover...",
        "likes": 7538,
        "dislikes": 54944,
        "created_at": "2023-09-20T21:40:25.891Z",
        "updated_at": "2023-09-21T10:15:12.244Z",
        "user_id": "user_entity_pk"
      },
      {
        "id": "6a399b09-50bd-4d43-af65-1534bc030e83",
        "title": "Adventures Around the World",
        "content": "Traveling is a way to...",
        "likes": 26443,
        "dislikes": 59840,
        "created_at": "2023-09-21T12:22:19.444Z",
        "updated_at": "2023-09-21T05:02:55.363Z",
        "user_id": "user_entity_pk"
      },
      {
        "id": "deeac0d1-4b9c-4622-b16b-91eed60dde14",
        "title": "Melodies of Life",
        "content": "Music has the power...",
        "likes": 89413,
        "dislikes": 73840,
        "created_at": "2023-09-21T04:25:03.050Z",
        "updated_at": "2023-09-21T00:48:22.723Z",
        "user_id": "user_entity_pk"
      },
      {
        "id": "3b0cea71-61f7-48b5-b61c-c61c6e0bea93",
        "title": "Unleashing the Athlete Within",
        "content": "Sports not only improve...",
        "likes": 81322,
        "dislikes": 33834,
        "created_at": "2023-09-21T00:09:52.454Z",
        "updated_at": "2023-09-21T07:45:31.602Z",
        "user_id": "user_entity_pk"
      }
    ],
    "post_tag": [
      {
        "id": "9be60c98-d3d3-467d-a040-830a387c4a5c",
        "created_at": "2023-09-21T09:53:56.186Z",
        "updated_at": "2023-09-21T16:58:45.996Z",
        "post_id": "deeac0d1-4b9c-4622-b16b-91eed60dde14",
        "tag_id": "1a1e780b-b83f-497e-b561-65a1f30e0bd8"
      },
      {
        "id": "f73d7f26-d758-4f3e-8318-93fc348e9fb3",
        "created_at": "2023-09-21T02:27:26.022Z",
        "updated_at": "2023-09-21T17:20:44.987Z",
        "post_id": "6a399b09-50bd-4d43-af65-1534bc030e83",
        "tag_id": "1c7a13c0-03d5-4f4e-a815-88cd8fc1f5cb"
      },
      {
        "id": "0eb35cd1-3f83-496d-819c-b4a910c80465",
        "created_at": "2023-09-21T14:19:12.143Z",
        "updated_at": "2023-09-21T09:04:15.559Z",
        "post_id": "3b0cea71-61f7-48b5-b61c-c61c6e0bea93",
        "tag_id": "94a8c466-8aaa-4f86-af08-f08262081ab0"
      },
      {
        "id": "3269b4e1-9be9-4cf1-8a1c-038becec8758",
        "created_at": "2023-09-21T13:07:25.230Z",
        "updated_at": "2023-09-21T17:30:15.994Z",
        "post_id": "44062436-6a25-472c-afb4-f63b2f80a25e",
        "tag_id": "94a8c466-8aaa-4f86-af08-f08262081ab0"
      },
      {
        "id": "090b5639-1b69-48e6-a937-83dcacf1894f",
        "created_at": "2023-09-21T14:50:38.901Z",
        "updated_at": "2023-09-20T18:01:01.927Z",
        "post_id": "bc888a31-94f0-4d27-86d7-832be21044db",
        "tag_id": "94a8c466-8aaa-4f86-af08-f08262081ab0"
      }
    ],
    "comment": [
      {
        "id": "aebad7f5-973a-49a2-b5ca-27f74aa486a3",
        "content": "Great post!",
        "likes": 5311,
        "dislikes": 37979,
        "created_at": "2023-09-20T20:48:38.050Z",
        "updated_at": "2023-09-21T13:03:12.765Z",
        "post_id": "bc888a31-94f0-4d27-86d7-832be21044db",
        "user_id": "user_entity_pk"
      },
      {
        "id": "f672d30d-ed1a-456d-9beb-13507f5ff2d9",
        "content": "I completely agree.",
        "likes": 72645,
        "dislikes": 92117,
        "created_at": "2023-09-20T19:36:25.702Z",
        "updated_at": "2023-09-21T14:28:22.579Z",
        "post_id": "3b0cea71-61f7-48b5-b61c-c61c6e0bea93",
        "user_id": "user_entity_pk"
      },
      {
        "id": "7960d7e1-482f-4833-a358-6efb1806e731",
        "content": "Interesting perspective.",
        "likes": 22819,
        "dislikes": 27064,
        "created_at": "2023-09-21T09:06:22.701Z",
        "updated_at": "2023-09-21T15:48:42.363Z",
        "post_id": "6a399b09-50bd-4d43-af65-1534bc030e83",
        "user_id": "user_entity_pk"
      },
      {
        "id": "aec4c734-3afb-4f48-ab8f-95007a1d8a92",
        "content": "Thanks for sharing.",
        "likes": 16467,
        "dislikes": 67693,
        "created_at": "2023-09-20T21:51:05.344Z",
        "updated_at": "2023-09-20T20:11:01.051Z",
        "post_id": "3b0cea71-61f7-48b5-b61c-c61c6e0bea93",
        "user_id": "user_entity_pk"
      },
      {
        "id": "0bbe589b-baad-4d68-82a3-917b4b55c13b",
        "content": "This is inspiring.",
        "likes": 2650,
        "dislikes": 73664,
        "created_at": "2023-09-20T21:39:47.340Z",
        "updated_at": "2023-09-21T08:52:48.235Z",
        "post_id": "44062436-6a25-472c-afb4-f63b2f80a25e",
        "user_id": "user_entity_pk"
      }
    ],
    "roqUser": [
      {
        "reference": "61450604-419d-4d11-bd18-0bf28f7cb198",
        "email": "Kole.Borer9@roq.tech",
        "firstName": "Jack",
        "lastName": "Stroman",
        "active": true,
        "avatarUrl": "https://avatars.githubusercontent.com/u/86304666",
        "tenantId": null
      },
      {
        "reference": "f9f9d4fb-23c2-47a8-a08a-c06e02cf769d",
        "email": "Floyd_Spinka@roq.tech",
        "firstName": "Cali",
        "lastName": "Medhurst",
        "active": true,
        "avatarUrl": "https://avatars.githubusercontent.com/u/75205143",
        "tenantId": null
      },
      {
        "reference": "8006080c-86c8-47ae-bd23-e795280506a0",
        "email": "Isadore93@roq.tech",
        "firstName": "Jammie",
        "lastName": "Farrell",
        "active": true,
        "avatarUrl": "https://cloudflare-ipfs.com/ipfs/Qmd3W5DuhgHirLHGVixi6V76LhCkZUz6pnFt5AJBiyvHye/avatar/182.jpg",
        "tenantId": null
      },
      {
        "reference": "e85ffa1f-88a1-4990-bfa4-ec74ba3d4a2a",
        "email": "Evangeline49@roq.tech",
        "firstName": "Uriah",
        "lastName": "Hegmann",
        "active": true,
        "avatarUrl": "https://avatars.githubusercontent.com/u/27718214",
        "tenantId": null
      },
      {
        "reference": "09399df7-9c70-4002-822a-0ac41519a312",
        "email": "Melissa_Block@roq.tech",
        "firstName": "Nelle",
        "lastName": "Considine",
        "active": true,
        "avatarUrl": "https://cloudflare-ipfs.com/ipfs/Qmd3W5DuhgHirLHGVixi6V76LhCkZUz6pnFt5AJBiyvHye/avatar/86.jpg",
        "tenantId": null
      }
    ]
  },
  {
    "tag": [
      {
        "id": "f2aa0253-76f8-4262-94db-2db290b3ab47",
        "name": "technology",
        "created_at": "2023-09-21T01:46:43.940Z",
        "updated_at": "2023-09-21T11:09:17.024Z"
      },
      {
        "id": "669424cb-3228-40d6-a49d-36712e64b5bf",
        "name": "food",
        "created_at": "2023-09-21T13:19:23.239Z",
        "updated_at": "2023-09-21T00:23:22.412Z"
      },
      {
        "id": "35349605-c4c4-4ff7-b301-848af8b49093",
        "name": "travel",
        "created_at": "2023-09-21T13:50:27.802Z",
        "updated_at": "2023-09-21T03:40:52.443Z"
      },
      {
        "id": "017ca5b2-95db-4711-ac21-a361e8b5d05d",
        "name": "music",
        "created_at": "2023-09-21T15:40:00.382Z",
        "updated_at": "2023-09-21T01:46:01.614Z"
      },
      {
        "id": "a6e707bc-1b28-440f-9f0e-31e5f8e559ac",
        "name": "sports",
        "created_at": "2023-09-21T15:42:26.513Z",
        "updated_at": "2023-09-21T06:33:30.823Z"
      }
    ],
    "post": [
      {
        "id": "d5405f4b-ad35-48da-bdcf-c92cfd28633f",
        "title": "The Importance of Education",
        "content": "Education plays a crucial role in shaping our future.",
        "likes": 48267,
        "dislikes": 3806,
        "created_at": "2023-09-21T04:11:58.964Z",
        "updated_at": "2023-09-20T20:33:00.015Z",
        "user_id": "user_entity_pk"
      },
      {
        "id": "235d4b59-5bc5-464e-bc9d-7fca3566dffb",
        "title": "Exploring New Culinary Delights",
        "content": "Discover the flavors of different cuisines and expand your palate.",
        "likes": 12176,
        "dislikes": 17440,
        "created_at": "2023-09-20T23:10:58.729Z",
        "updated_at": "2023-09-20T21:10:05.822Z",
        "user_id": "user_entity_pk"
      },
      {
        "id": "17bfde90-5e4a-4f77-82c8-48f28c2155cc",
        "title": "Unforgettable Travel Experiences",
        "content": "Embark on thrilling adventures and create lifelong memories.",
        "likes": 59295,
        "dislikes": 71420,
        "created_at": "2023-09-21T17:46:38.720Z",
        "updated_at": "2023-09-21T14:18:51.578Z",
        "user_id": "user_entity_pk"
      },
      {
        "id": "f06a10b3-f0f3-44b4-be8a-ae20c2a34556",
        "title": "The Power of Music",
        "content": "Music has the ability to touch our souls and evoke emotions.",
        "likes": 58746,
        "dislikes": 14242,
        "created_at": "2023-09-21T14:54:58.752Z",
        "updated_at": "2023-09-21T16:54:05.486Z",
        "user_id": "user_entity_pk"
      },
      {
        "id": "bc7b9a9a-0517-46dd-a9a6-3f80d13b5e7b",
        "title": "Achieving Success in Sports",
        "content": "Sports teach us valuable lessons about teamwork, discipline, and perseverance.",
        "likes": 32474,
        "dislikes": 876,
        "created_at": "2023-09-21T12:37:01.456Z",
        "updated_at": "2023-09-21T05:22:26.252Z",
        "user_id": "user_entity_pk"
      }
    ],
    "post_tag": [
      {
        "id": "48a331a2-7911-43a0-961a-b2582699d647",
        "created_at": "2023-09-20T18:09:54.543Z",
        "updated_at": "2023-09-20T22:00:06.217Z",
        "post_id": "bc7b9a9a-0517-46dd-a9a6-3f80d13b5e7b",
        "tag_id": "35349605-c4c4-4ff7-b301-848af8b49093"
      },
      {
        "id": "396a4f1d-32d0-4979-86b0-00e4b3e08f1f",
        "created_at": "2023-09-21T17:25:59.939Z",
        "updated_at": "2023-09-20T19:38:26.838Z",
        "post_id": "f06a10b3-f0f3-44b4-be8a-ae20c2a34556",
        "tag_id": "f2aa0253-76f8-4262-94db-2db290b3ab47"
      },
      {
        "id": "4a3525fc-894f-467d-b9ef-ea94509abc35",
        "created_at": "2023-09-20T20:19:15.699Z",
        "updated_at": "2023-09-21T08:28:51.513Z",
        "post_id": "bc7b9a9a-0517-46dd-a9a6-3f80d13b5e7b",
        "tag_id": "35349605-c4c4-4ff7-b301-848af8b49093"
      },
      {
        "id": "a54b3459-1ad3-41a6-8b01-a940759b5d6a",
        "created_at": "2023-09-20T18:09:57.892Z",
        "updated_at": "2023-09-21T15:22:09.207Z",
        "post_id": "17bfde90-5e4a-4f77-82c8-48f28c2155cc",
        "tag_id": "a6e707bc-1b28-440f-9f0e-31e5f8e559ac"
      },
      {
        "id": "86b21f9b-788d-4fe5-85c3-3cc74f81db52",
        "created_at": "2023-09-21T06:11:35.152Z",
        "updated_at": "2023-09-21T12:01:10.481Z",
        "post_id": "bc7b9a9a-0517-46dd-a9a6-3f80d13b5e7b",
        "tag_id": "a6e707bc-1b28-440f-9f0e-31e5f8e559ac"
      }
    ],
    "comment": [
      {
        "id": "887a36cf-9365-4659-b94c-d92437de98c8",
        "content": "Great article!",
        "likes": 62276,
        "dislikes": 82188,
        "created_at": "2023-09-21T03:54:40.515Z",
        "updated_at": "2023-09-21T09:47:35.032Z",
        "post_id": "bc7b9a9a-0517-46dd-a9a6-3f80d13b5e7b",
        "user_id": "user_entity_pk"
      },
      {
        "id": "d30deacd-d1e5-48de-b531-9dd8a31dca31",
        "content": "I completely agree.",
        "likes": 56254,
        "dislikes": 9098,
        "created_at": "2023-09-21T14:07:10.752Z",
        "updated_at": "2023-09-20T22:00:23.906Z",
        "post_id": "d5405f4b-ad35-48da-bdcf-c92cfd28633f",
        "user_id": "user_entity_pk"
      },
      {
        "id": "c0baa70a-830e-4c3f-bd14-5934ebac1870",
        "content": "Thanks for sharing.",
        "likes": 87526,
        "dislikes": 88,
        "created_at": "2023-09-21T00:06:16.826Z",
        "updated_at": "2023-09-21T03:25:47.755Z",
        "post_id": "bc7b9a9a-0517-46dd-a9a6-3f80d13b5e7b",
        "user_id": "user_entity_pk"
      },
      {
        "id": "1b53e96b-1a06-48a9-880d-196423ba26c5",
        "content": "Interesting perspective.",
        "likes": 59185,
        "dislikes": 80361,
        "created_at": "2023-09-20T23:21:24.833Z",
        "updated_at": "2023-09-20T22:35:25.780Z",
        "post_id": "d5405f4b-ad35-48da-bdcf-c92cfd28633f",
        "user_id": "user_entity_pk"
      },
      {
        "id": "4cd66d71-6249-47e5-be8a-52f7dd3c7c8e",
        "content": "Well written.",
        "likes": 85794,
        "dislikes": 84184,
        "created_at": "2023-09-21T00:36:07.209Z",
        "updated_at": "2023-09-20T23:47:04.479Z",
        "post_id": "bc7b9a9a-0517-46dd-a9a6-3f80d13b5e7b",
        "user_id": "user_entity_pk"
      }
    ],
    "roqUser": [
      {
        "reference": "54b02d1d-7a85-4a8e-996d-e5dda7cf1c21",
        "email": "Kathryn_Anderson64@roq.tech",
        "firstName": "Greyson",
        "lastName": "Mann",
        "active": true,
        "avatarUrl": "https://cloudflare-ipfs.com/ipfs/Qmd3W5DuhgHirLHGVixi6V76LhCkZUz6pnFt5AJBiyvHye/avatar/899.jpg",
        "tenantId": null
      },
      {
        "reference": "f9e91a29-ca9e-490a-85ae-a3bd614a14aa",
        "email": "Piper41@roq.tech",
        "firstName": "Saul",
        "lastName": "Block",
        "active": true,
        "avatarUrl": "https://avatars.githubusercontent.com/u/72254128",
        "tenantId": null
      },
      {
        "reference": "1d64cd59-20a8-4d82-accc-0b7dd4f2af28",
        "email": "Jayda54@roq.tech",
        "firstName": "Loyal",
        "lastName": "Schiller",
        "active": true,
        "avatarUrl": "https://cloudflare-ipfs.com/ipfs/Qmd3W5DuhgHirLHGVixi6V76LhCkZUz6pnFt5AJBiyvHye/avatar/849.jpg",
        "tenantId": null
      },
      {
        "reference": "8abb08b2-864e-4912-8127-3c1507b12fab",
        "email": "Carroll_Fisher7@roq.tech",
        "firstName": "Scot",
        "lastName": "Lang",
        "active": true,
        "avatarUrl": "https://avatars.githubusercontent.com/u/58048285",
        "tenantId": null
      },
      {
        "reference": "89950689-8628-4c0f-8bb9-5753bd578e00",
        "email": "Cleo_Ortiz68@roq.tech",
        "firstName": "Rusty",
        "lastName": "Oberbrunner",
        "active": true,
        "avatarUrl": "https://avatars.githubusercontent.com/u/52701847",
        "tenantId": null
      }
    ]
  },
  {
    "tag": [
      {
        "id": "7a0c719d-df59-49c7-bc2d-ced98ef15d61",
        "name": "Technology",
        "created_at": "2023-09-20T21:37:22.980Z",
        "updated_at": "2023-09-21T04:11:57.544Z"
      },
      {
        "id": "b7db68e7-dee9-4ace-9178-eb24ecb9dca6",
        "name": "Fashion",
        "created_at": "2023-09-21T00:43:25.478Z",
        "updated_at": "2023-09-20T20:30:13.919Z"
      },
      {
        "id": "a70e474d-d033-4ebd-8e82-bda607ac3c62",
        "name": "Food",
        "created_at": "2023-09-21T16:58:25.507Z",
        "updated_at": "2023-09-20T19:10:12.812Z"
      },
      {
        "id": "48101d24-2a65-4b28-b9af-53dcf75e1548",
        "name": "Travel",
        "created_at": "2023-09-21T06:49:08.256Z",
        "updated_at": "2023-09-21T17:20:01.939Z"
      },
      {
        "id": "750b2980-368f-4996-b1a9-f1963537e35a",
        "name": "Sports",
        "created_at": "2023-09-20T22:53:02.219Z",
        "updated_at": "2023-09-21T00:44:43.083Z"
      }
    ],
    "post": [
      {
        "id": "66c0faad-97b3-44d2-8d91-f703f04f58b1",
        "title": "The Future of AI",
        "content": "Lorem ipsum dolor sit amet, consectetur adipiscing elit.",
        "likes": 21102,
        "dislikes": 71781,
        "created_at": "2023-09-20T17:56:35.620Z",
        "updated_at": "2023-09-20T22:55:50.062Z",
        "user_id": "user_entity_pk"
      },
      {
        "id": "c84535c5-7c3b-412e-bda2-dbb867317595",
        "title": "Latest Fashion Trends",
        "content": "Sed ut perspiciatis unde omnis iste natus error sit voluptatem accusantium doloremque laudantium.",
        "likes": 18623,
        "dislikes": 69145,
        "created_at": "2023-09-20T20:25:20.949Z",
        "updated_at": "2023-09-21T03:49:36.594Z",
        "user_id": "user_entity_pk"
      },
      {
        "id": "01712a92-b144-4da9-9809-930419774fbc",
        "title": "Delicious Recipes to Try",
        "content": "Nemo enim ipsam voluptatem quia voluptas sit aspernatur aut odit aut fugit.",
        "likes": 78034,
        "dislikes": 11047,
        "created_at": "2023-09-21T12:26:55.259Z",
        "updated_at": "2023-09-20T18:30:55.958Z",
        "user_id": "user_entity_pk"
      },
      {
        "id": "9a24cc04-d6b2-4eca-b9e2-4ef561ce6845",
        "title": "Top Travel Destinations",
        "content": "Ut enim ad minima veniam, quis nostrum exercitationem ullam corporis suscipit laboriosam.",
        "likes": 25998,
        "dislikes": 42677,
        "created_at": "2023-09-21T14:56:31.405Z",
        "updated_at": "2023-09-21T02:43:11.899Z",
        "user_id": "user_entity_pk"
      },
      {
        "id": "c6549253-1ea9-4bae-a5f1-67fdb15fff9c",
        "title": "Sports Events to Attend",
        "content": "Duis aute irure dolor in reprehenderit in voluptate velit esse cillum dolore eu fugiat nulla pariatur.",
        "likes": 81514,
        "dislikes": 77882,
        "created_at": "2023-09-21T04:18:27.788Z",
        "updated_at": "2023-09-21T00:43:10.340Z",
        "user_id": "user_entity_pk"
      }
    ],
    "post_tag": [
      {
        "id": "0847d971-65f6-4f2d-a751-abe287355e63",
        "created_at": "2023-09-21T04:11:47.013Z",
        "updated_at": "2023-09-21T01:38:25.595Z",
        "post_id": "9a24cc04-d6b2-4eca-b9e2-4ef561ce6845",
        "tag_id": "48101d24-2a65-4b28-b9af-53dcf75e1548"
      },
      {
        "id": "a881b4fc-3caf-4b3c-9280-2cc1e9b981bb",
        "created_at": "2023-09-21T12:12:51.516Z",
        "updated_at": "2023-09-21T10:11:09.141Z",
        "post_id": "c84535c5-7c3b-412e-bda2-dbb867317595",
        "tag_id": "a70e474d-d033-4ebd-8e82-bda607ac3c62"
      },
      {
        "id": "d0bd2ec2-bfc7-4a59-a651-b9f8a547ce50",
        "created_at": "2023-09-21T04:49:36.599Z",
        "updated_at": "2023-09-21T08:21:14.582Z",
        "post_id": "66c0faad-97b3-44d2-8d91-f703f04f58b1",
        "tag_id": "7a0c719d-df59-49c7-bc2d-ced98ef15d61"
      },
      {
        "id": "5f95610b-e2a3-4500-9a68-e3bac85830a0",
        "created_at": "2023-09-20T19:09:12.148Z",
        "updated_at": "2023-09-20T18:25:46.415Z",
        "post_id": "66c0faad-97b3-44d2-8d91-f703f04f58b1",
        "tag_id": "b7db68e7-dee9-4ace-9178-eb24ecb9dca6"
      },
      {
        "id": "3c159403-c7dd-478a-ad9d-72a3a9abc9ea",
        "created_at": "2023-09-21T04:03:03.491Z",
        "updated_at": "2023-09-20T18:05:40.617Z",
        "post_id": "c6549253-1ea9-4bae-a5f1-67fdb15fff9c",
        "tag_id": "7a0c719d-df59-49c7-bc2d-ced98ef15d61"
      }
    ],
    "comment": [
      {
        "id": "749f5f63-54dc-4531-9b46-937bb8a3d298",
        "content": "Great article!",
        "likes": 51042,
        "dislikes": 12901,
        "created_at": "2023-09-21T14:37:02.251Z",
        "updated_at": "2023-09-21T01:58:59.612Z",
        "post_id": "66c0faad-97b3-44d2-8d91-f703f04f58b1",
        "user_id": "user_entity_pk"
      },
      {
        "id": "0c709a7d-8df2-488b-a475-fc9410b459a2",
        "content": "I completely agree.",
        "likes": 85430,
        "dislikes": 4235,
        "created_at": "2023-09-21T03:55:58.661Z",
        "updated_at": "2023-09-21T09:50:54.929Z",
        "post_id": "c84535c5-7c3b-412e-bda2-dbb867317595",
        "user_id": "user_entity_pk"
      },
      {
        "id": "e570ed8f-eb0f-4f19-9a50-9509bfd33ddc",
        "content": "Interesting perspective.",
        "likes": 91564,
        "dislikes": 95349,
        "created_at": "2023-09-21T08:58:22.929Z",
        "updated_at": "2023-09-20T21:02:35.764Z",
        "post_id": "9a24cc04-d6b2-4eca-b9e2-4ef561ce6845",
        "user_id": "user_entity_pk"
      },
      {
        "id": "46cf7a41-d156-4767-a18e-af437395d9d0",
        "content": "Thanks for sharing!",
        "likes": 17976,
        "dislikes": 41199,
        "created_at": "2023-09-21T07:58:17.785Z",
        "updated_at": "2023-09-21T13:00:36.363Z",
        "post_id": "c6549253-1ea9-4bae-a5f1-67fdb15fff9c",
        "user_id": "user_entity_pk"
      },
      {
        "id": "93a04a1b-2156-4a7e-b6d7-b9bfe118fe7e",
        "content": "Well written.",
        "likes": 49767,
        "dislikes": 43192,
        "created_at": "2023-09-21T04:43:13.385Z",
        "updated_at": "2023-09-21T13:44:02.933Z",
        "post_id": "c84535c5-7c3b-412e-bda2-dbb867317595",
        "user_id": "user_entity_pk"
      }
    ],
    "roqUser": [
      {
        "reference": "1bf910ad-5b88-4ce0-a2e1-f38c3a49e86e",
        "email": "Monserrate.Quitzon60@roq.tech",
        "firstName": "Marielle",
        "lastName": "Schultz",
        "active": true,
        "avatarUrl": "https://avatars.githubusercontent.com/u/49013595",
        "tenantId": null
      },
      {
        "reference": "4ccb6680-f771-4292-b847-3cf8cc99dd37",
        "email": "John_Ankunding@roq.tech",
        "firstName": "Preston",
        "lastName": "Quitzon",
        "active": true,
        "avatarUrl": "https://cloudflare-ipfs.com/ipfs/Qmd3W5DuhgHirLHGVixi6V76LhCkZUz6pnFt5AJBiyvHye/avatar/964.jpg",
        "tenantId": null
      },
      {
        "reference": "2ce449ca-c390-49d7-a56e-f10f29664167",
        "email": "Haley_Wunsch21@roq.tech",
        "firstName": "Bettie",
        "lastName": "Douglas",
        "active": true,
        "avatarUrl": "https://avatars.githubusercontent.com/u/95284957",
        "tenantId": null
      },
      {
        "reference": "6b5076d6-b2c0-4178-995e-ff6304fef063",
        "email": "Loraine69@roq.tech",
        "firstName": "Camron",
        "lastName": "Bernier",
        "active": true,
        "avatarUrl": "https://cloudflare-ipfs.com/ipfs/Qmd3W5DuhgHirLHGVixi6V76LhCkZUz6pnFt5AJBiyvHye/avatar/178.jpg",
        "tenantId": null
      },
      {
        "reference": "44a717bf-5f6a-4bee-b409-574441d9f009",
        "email": "Eliezer41@roq.tech",
        "firstName": "Domenic",
        "lastName": "Strosin",
        "active": true,
        "avatarUrl": "https://cloudflare-ipfs.com/ipfs/Qmd3W5DuhgHirLHGVixi6V76LhCkZUz6pnFt5AJBiyvHye/avatar/835.jpg",
        "tenantId": null
      }
    ]
  },
  {
    "tag": [
      {
        "id": "110b4db3-8628-4e3d-bf2c-f164da6d7ec8",
        "name": "technology",
        "created_at": "2023-09-21T07:34:47.223Z",
        "updated_at": "2023-09-21T12:33:00.571Z"
      },
      {
        "id": "3cbe0243-4f60-47a8-8098-b17c56303f41",
        "name": "food",
        "created_at": "2023-09-20T22:53:47.556Z",
        "updated_at": "2023-09-21T02:24:11.551Z"
      },
      {
        "id": "a7965445-6965-45fb-8f88-621c639900a2",
        "name": "travel",
        "created_at": "2023-09-20T21:26:26.320Z",
        "updated_at": "2023-09-20T19:01:37.562Z"
      },
      {
        "id": "2f69b42f-471b-4c7d-bbf8-e7578fea7276",
        "name": "music",
        "created_at": "2023-09-20T21:53:25.524Z",
        "updated_at": "2023-09-20T19:51:22.101Z"
      },
      {
        "id": "8b440067-7351-4034-8a74-ee7f8b16f6ba",
        "name": "sports",
        "created_at": "2023-09-20T22:55:10.257Z",
        "updated_at": "2023-09-21T07:40:41.467Z"
      }
    ],
    "post": [
      {
        "id": "1bdb2d81-c359-4344-958b-e2db565f7c2b",
        "title": "The Importance of Education",
        "content": "Education plays a crucial role in shaping our future.",
        "likes": 58257,
        "dislikes": 31671,
        "created_at": "2023-09-21T13:53:28.590Z",
        "updated_at": "2023-09-21T01:49:26.175Z",
        "user_id": "user_entity_pk"
      },
      {
        "id": "97ea7fcd-811f-4172-8855-38aa00f9376b",
        "title": "Exploring New Culinary Delights",
        "content": "Indulge in a gastronomic journey with these unique recipes.",
        "likes": 17539,
        "dislikes": 59036,
        "created_at": "2023-09-20T18:21:30.558Z",
        "updated_at": "2023-09-21T08:23:35.165Z",
        "user_id": "user_entity_pk"
      },
      {
        "id": "77336909-cfa8-43f4-8272-950ae9acffe5",
        "title": "Unforgettable Adventures in Europe",
        "content": "Embark on a thrilling journey through the picturesque landscapes of Europe.",
        "likes": 19173,
        "dislikes": 89211,
        "created_at": "2023-09-21T01:59:56.382Z",
        "updated_at": "2023-09-21T17:46:10.809Z",
        "user_id": "user_entity_pk"
      },
      {
        "id": "b79b77f5-7bcd-433e-9117-f72b73dcb001",
        "title": "The Power of Music",
        "content": "Music has the ability to evoke powerful emotions.",
        "likes": 82260,
        "dislikes": 3555,
        "created_at": "2023-09-21T06:46:07.248Z",
        "updated_at": "2023-09-21T11:19:13.071Z",
        "user_id": "user_entity_pk"
      },
      {
        "id": "3bb24519-96cd-48b5-ad90-7307a04b5c0a",
        "title": "Achieving Fitness Goals",
        "content": "Stay motivated and achieve your fitness goals with these effective tips.",
        "likes": 79631,
        "dislikes": 87635,
        "created_at": "2023-09-21T12:56:42.742Z",
        "updated_at": "2023-09-20T23:54:28.538Z",
        "user_id": "user_entity_pk"
      }
    ],
    "post_tag": [
      {
        "id": "632e9234-830d-4153-86e2-415cd0152de9",
        "created_at": "2023-09-20T23:02:34.340Z",
        "updated_at": "2023-09-21T10:28:42.467Z",
        "post_id": "3bb24519-96cd-48b5-ad90-7307a04b5c0a",
        "tag_id": "a7965445-6965-45fb-8f88-621c639900a2"
      },
      {
        "id": "df3924a1-fb17-43da-b6a8-3c8e81cd492e",
        "created_at": "2023-09-20T19:29:53.486Z",
        "updated_at": "2023-09-21T12:17:02.939Z",
        "post_id": "77336909-cfa8-43f4-8272-950ae9acffe5",
        "tag_id": "110b4db3-8628-4e3d-bf2c-f164da6d7ec8"
      },
      {
        "id": "e6fe1102-1cb1-4fd7-82b7-a285380b4376",
        "created_at": "2023-09-21T04:57:18.591Z",
        "updated_at": "2023-09-21T01:44:24.062Z",
        "post_id": "b79b77f5-7bcd-433e-9117-f72b73dcb001",
        "tag_id": "3cbe0243-4f60-47a8-8098-b17c56303f41"
      },
      {
        "id": "20faef00-6801-4f2d-9a73-8e8081493199",
        "created_at": "2023-09-20T20:40:38.989Z",
        "updated_at": "2023-09-21T07:28:15.069Z",
        "post_id": "b79b77f5-7bcd-433e-9117-f72b73dcb001",
        "tag_id": "8b440067-7351-4034-8a74-ee7f8b16f6ba"
      },
      {
        "id": "327d4c8e-5f6f-409a-af78-653f231132cd",
        "created_at": "2023-09-21T17:47:51.713Z",
        "updated_at": "2023-09-20T19:55:42.893Z",
        "post_id": "b79b77f5-7bcd-433e-9117-f72b73dcb001",
        "tag_id": "2f69b42f-471b-4c7d-bbf8-e7578fea7276"
      }
    ],
    "comment": [
      {
        "id": "24f03a76-142f-4f15-92d4-1f05c57fcd57",
        "content": "Great article!",
        "likes": 64499,
        "dislikes": 35732,
        "created_at": "2023-09-21T11:08:38.662Z",
        "updated_at": "2023-09-21T00:07:34.231Z",
        "post_id": "1bdb2d81-c359-4344-958b-e2db565f7c2b",
        "user_id": "user_entity_pk"
      },
      {
        "id": "fdcd3b16-1f6e-48c4-a9bb-b80a59381c59",
        "content": "I completely agree.",
        "likes": 8398,
        "dislikes": 24229,
        "created_at": "2023-09-21T08:46:37.485Z",
        "updated_at": "2023-09-21T06:03:49.953Z",
        "post_id": "77336909-cfa8-43f4-8272-950ae9acffe5",
        "user_id": "user_entity_pk"
      },
      {
        "id": "ef203eb5-3886-4388-970e-9196a2e3c9b0",
        "content": "Thanks for sharing.",
        "likes": 30251,
        "dislikes": 91746,
        "created_at": "2023-09-21T06:49:43.447Z",
        "updated_at": "2023-09-21T09:56:28.996Z",
        "post_id": "1bdb2d81-c359-4344-958b-e2db565f7c2b",
        "user_id": "user_entity_pk"
      },
      {
        "id": "bea57391-4e34-4e5b-b18c-9196564345d5",
        "content": "Interesting perspective.",
        "likes": 67095,
        "dislikes": 16567,
        "created_at": "2023-09-21T09:33:06.559Z",
        "updated_at": "2023-09-21T03:14:14.901Z",
        "post_id": "b79b77f5-7bcd-433e-9117-f72b73dcb001",
        "user_id": "user_entity_pk"
      },
      {
        "id": "3c47d27c-4df7-48cf-8fc9-757c6cfa344b",
        "content": "Well written.",
        "likes": 34462,
        "dislikes": 80144,
        "created_at": "2023-09-21T04:19:44.223Z",
        "updated_at": "2023-09-21T01:01:22.544Z",
        "post_id": "3bb24519-96cd-48b5-ad90-7307a04b5c0a",
        "user_id": "user_entity_pk"
      }
    ],
    "roqUser": [
      {
        "reference": "9a88fa2c-0be0-49eb-bc26-908a58581fb5",
        "email": "Palma74@roq.tech",
        "firstName": "Madalyn",
        "lastName": "Schmitt",
        "active": true,
        "avatarUrl": "https://avatars.githubusercontent.com/u/65011423",
        "tenantId": null
      },
      {
        "reference": "1328e76f-8fd2-4b31-be86-b84bded5d51f",
        "email": "Noe45@roq.tech",
        "firstName": "Vincent",
        "lastName": "Romaguera",
        "active": true,
        "avatarUrl": "https://cloudflare-ipfs.com/ipfs/Qmd3W5DuhgHirLHGVixi6V76LhCkZUz6pnFt5AJBiyvHye/avatar/502.jpg",
        "tenantId": null
      },
      {
        "reference": "86cce541-88ca-4214-b8db-d50e78d486bd",
        "email": "Leanne53@roq.tech",
        "firstName": "Mavis",
        "lastName": "VonRueden",
        "active": true,
        "avatarUrl": "https://cloudflare-ipfs.com/ipfs/Qmd3W5DuhgHirLHGVixi6V76LhCkZUz6pnFt5AJBiyvHye/avatar/537.jpg",
        "tenantId": null
      },
      {
        "reference": "61d7543e-d33e-456a-903b-139c8e4efdbf",
        "email": "Gregory_Cronin@roq.tech",
        "firstName": "Carolyn",
        "lastName": "Schuppe-Koelpin",
        "active": true,
        "avatarUrl": "https://cloudflare-ipfs.com/ipfs/Qmd3W5DuhgHirLHGVixi6V76LhCkZUz6pnFt5AJBiyvHye/avatar/56.jpg",
        "tenantId": null
      },
      {
        "reference": "c9b1967b-98d2-4bbb-81bb-81a80c928546",
        "email": "Dorcas26@roq.tech",
        "firstName": "Anita",
        "lastName": "Bernier",
        "active": true,
        "avatarUrl": "https://cloudflare-ipfs.com/ipfs/Qmd3W5DuhgHirLHGVixi6V76LhCkZUz6pnFt5AJBiyvHye/avatar/501.jpg",
        "tenantId": null
      }
    ]
  },
  {
    "tag": [
      {
        "id": "70bad8b5-5845-42f9-8062-aa1d5a0eb9c2",
        "name": "Technology",
        "created_at": "2023-09-21T06:26:07.594Z",
        "updated_at": "2023-09-21T08:01:35.478Z"
      },
      {
        "id": "041bc0dd-7c38-41e2-892d-cf38fc929b9a",
        "name": "Food",
        "created_at": "2023-09-21T03:40:56.694Z",
        "updated_at": "2023-09-20T18:41:10.948Z"
      },
      {
        "id": "3fc28225-ba1a-43f9-aa33-1634ee6ef7a9",
        "name": "Travel",
        "created_at": "2023-09-21T02:06:23.856Z",
        "updated_at": "2023-09-21T13:58:20.797Z"
      },
      {
        "id": "4db2e3da-49d9-4c25-992f-d94e572af13b",
        "name": "Fashion",
        "created_at": "2023-09-21T09:21:22.005Z",
        "updated_at": "2023-09-21T15:54:22.015Z"
      },
      {
        "id": "f4bf98ff-584a-438e-8e1f-365023f0a343",
        "name": "Sports",
        "created_at": "2023-09-21T09:55:25.189Z",
        "updated_at": "2023-09-20T22:30:58.275Z"
      }
    ],
    "post": [
      {
        "id": "a4927666-b49f-46a0-80ae-594f3b98f230",
        "title": "Introduction to Machine Learning",
        "content": "Lorem ipsum dolor sit amet, consectetur adipiscing elit.",
        "likes": 42315,
        "dislikes": 96355,
        "created_at": "2023-09-20T23:55:29.155Z",
        "updated_at": "2023-09-20T18:56:41.981Z",
        "user_id": "user_entity_pk"
      },
      {
        "id": "648ac324-bc1e-4002-8595-48b25be12417",
        "title": "Delicious Recipes for Dinner",
        "content": "Sed ut perspiciatis unde omnis iste natus error sit voluptatem.",
        "likes": 26373,
        "dislikes": 66584,
        "created_at": "2023-09-21T01:53:34.582Z",
        "updated_at": "2023-09-21T00:23:02.609Z",
        "user_id": "user_entity_pk"
      },
      {
        "id": "c84326e5-179f-4e31-b296-968dced83c44",
        "title": "Exploring the Wonders of Bali",
        "content": "Nemo enim ipsam voluptatem quia voluptas sit aspernatur aut odit aut fugit.",
        "likes": 89651,
        "dislikes": 14027,
        "created_at": "2023-09-20T20:39:39.490Z",
        "updated_at": "2023-09-21T03:43:24.615Z",
        "user_id": "user_entity_pk"
      },
      {
        "id": "7ac21272-3537-4511-bfbc-b5913f9192c9",
        "title": "Latest Fashion Trends",
        "content": "Neque porro quisquam est, qui dolorem ipsum quia dolor sit amet.",
        "likes": 93382,
        "dislikes": 17217,
        "created_at": "2023-09-21T02:10:56.931Z",
        "updated_at": "2023-09-21T11:45:42.857Z",
        "user_id": "user_entity_pk"
      },
      {
        "id": "276d8dc2-d037-4991-9f9f-3432809cf355",
        "title": "Top 10 Sports Moments",
        "content": "Consectetur, adipisci velit, sed quia non numquam eius modi tempora.",
        "likes": 56918,
        "dislikes": 52113,
        "created_at": "2023-09-21T02:44:30.354Z",
        "updated_at": "2023-09-21T15:38:53.761Z",
        "user_id": "user_entity_pk"
      }
    ],
    "post_tag": [
      {
        "id": "5cce58d6-40be-4b5e-a128-9d58ff5fddc8",
        "created_at": "2023-09-21T12:58:38.512Z",
        "updated_at": "2023-09-21T15:00:20.874Z",
        "post_id": "c84326e5-179f-4e31-b296-968dced83c44",
        "tag_id": "041bc0dd-7c38-41e2-892d-cf38fc929b9a"
      },
      {
        "id": "93f04750-ad95-4074-9f2d-90061a6e07b2",
        "created_at": "2023-09-20T21:13:02.408Z",
        "updated_at": "2023-09-21T11:00:14.399Z",
        "post_id": "7ac21272-3537-4511-bfbc-b5913f9192c9",
        "tag_id": "70bad8b5-5845-42f9-8062-aa1d5a0eb9c2"
      },
      {
        "id": "ca1e1c60-c0db-44f8-ab6a-2b30270ef9cf",
        "created_at": "2023-09-21T01:10:42.928Z",
        "updated_at": "2023-09-21T02:35:13.041Z",
        "post_id": "276d8dc2-d037-4991-9f9f-3432809cf355",
        "tag_id": "041bc0dd-7c38-41e2-892d-cf38fc929b9a"
      },
      {
        "id": "1000b695-dc52-4eb2-ac4d-6ca619d8423e",
        "created_at": "2023-09-20T19:56:23.333Z",
        "updated_at": "2023-09-20T19:57:03.465Z",
        "post_id": "c84326e5-179f-4e31-b296-968dced83c44",
        "tag_id": "4db2e3da-49d9-4c25-992f-d94e572af13b"
      },
      {
        "id": "ce0ae52b-1b19-487a-a765-e85812c55c4a",
        "created_at": "2023-09-21T05:59:47.781Z",
        "updated_at": "2023-09-21T07:10:19.650Z",
        "post_id": "7ac21272-3537-4511-bfbc-b5913f9192c9",
        "tag_id": "70bad8b5-5845-42f9-8062-aa1d5a0eb9c2"
      }
    ],
    "comment": [
      {
        "id": "e9b01e27-f1d8-4e80-8a0b-c732d8e3ead7",
        "content": "Great article!",
        "likes": 86279,
        "dislikes": 34042,
        "created_at": "2023-09-21T13:52:27.870Z",
        "updated_at": "2023-09-21T12:12:32.923Z",
        "post_id": "648ac324-bc1e-4002-8595-48b25be12417",
        "user_id": "user_entity_pk"
      },
      {
        "id": "ecf741aa-12ea-4997-877e-a4001caf268b",
        "content": "I tried this recipe and it was amazing.",
        "likes": 10067,
        "dislikes": 9908,
        "created_at": "2023-09-21T05:05:26.881Z",
        "updated_at": "2023-09-21T06:36:09.457Z",
        "post_id": "c84326e5-179f-4e31-b296-968dced83c44",
        "user_id": "user_entity_pk"
      },
      {
        "id": "c22c11f2-3767-4928-a282-e9aa9748d74e",
        "content": "I love traveling and this destination looks incredible.",
        "likes": 32574,
        "dislikes": 69957,
        "created_at": "2023-09-21T06:57:43.912Z",
        "updated_at": "2023-09-21T03:44:02.021Z",
        "post_id": "7ac21272-3537-4511-bfbc-b5913f9192c9",
        "user_id": "user_entity_pk"
      },
      {
        "id": "63574988-76c4-4b0a-a084-198a73852fff",
        "content": "The fashion industry is always evolving.",
        "likes": 42876,
        "dislikes": 74189,
        "created_at": "2023-09-21T01:05:43.971Z",
        "updated_at": "2023-09-21T11:53:42.344Z",
        "post_id": "c84326e5-179f-4e31-b296-968dced83c44",
        "user_id": "user_entity_pk"
      },
      {
        "id": "8f1efb3e-0a4e-4b85-af85-f5d2f2325442",
        "content": "What a thrilling sports event!",
        "likes": 76457,
        "dislikes": 51308,
        "created_at": "2023-09-21T04:31:03.403Z",
        "updated_at": "2023-09-21T08:38:01.449Z",
        "post_id": "c84326e5-179f-4e31-b296-968dced83c44",
        "user_id": "user_entity_pk"
      }
    ],
    "roqUser": [
      {
        "reference": "fd93bfb1-1ad8-43ae-9110-0771aa8a2ac1",
        "email": "Markus74@roq.tech",
        "firstName": "Lonnie",
        "lastName": "Rippin",
        "active": true,
        "avatarUrl": "https://avatars.githubusercontent.com/u/70330734",
        "tenantId": null
      },
      {
        "reference": "35a46159-bac8-486e-9700-d67269128f09",
        "email": "Mathew.OConner@roq.tech",
        "firstName": "Alfredo",
        "lastName": "Douglas",
        "active": true,
        "avatarUrl": "https://avatars.githubusercontent.com/u/47579036",
        "tenantId": null
      },
      {
        "reference": "289ddc61-7dc6-4178-a754-a1f0d3f1d178",
        "email": "Aletha99@roq.tech",
        "firstName": "Benny",
        "lastName": "Sanford",
        "active": true,
        "avatarUrl": "https://avatars.githubusercontent.com/u/27567698",
        "tenantId": null
      },
      {
        "reference": "0cc6076f-51d9-434a-a878-1237b1e1b561",
        "email": "Maryjane1@roq.tech",
        "firstName": "Ozella",
        "lastName": "Cronin",
        "active": true,
        "avatarUrl": "https://cloudflare-ipfs.com/ipfs/Qmd3W5DuhgHirLHGVixi6V76LhCkZUz6pnFt5AJBiyvHye/avatar/743.jpg",
        "tenantId": null
      },
      {
        "reference": "83eba802-6b2f-4ff1-a858-9f93d3314f80",
        "email": "Lavon40@roq.tech",
        "firstName": "Frederique",
        "lastName": "Bernier",
        "active": true,
        "avatarUrl": "https://cloudflare-ipfs.com/ipfs/Qmd3W5DuhgHirLHGVixi6V76LhCkZUz6pnFt5AJBiyvHye/avatar/517.jpg",
        "tenantId": null
      }
    ]
  }
]
